{
  "ordinal": {
    "1": "Primeira",
    "2": "Segunda",
    "3": "Terceira",
    "4": "Quarta",
    "5": "Quinta",
    "n": "{n}ª"
  },
  "templates": {
    "worldWar": "{ordinal} Guerra Mundial",
    "greatWar": "Grande Guerra entre {A} e {B} (+{n} civilizações)",
    "tripartite": "Guerra tripartida {A}–{B}–{C}",
    "bilateral": "{ordinal} Guerra entre {A} e {B}"
  },
  "ui": {
    "attackers": "Atacantes:",
    "defenders": "Defensores:",
    "declaredBy": "Declarada por:",
    "years": "anos",
    "turns": "turnos",
    "concluded": "concluída",
    "ongoing": "em curso"
  },
  "civAdjectives": {
    "America": "América",
    "Arabia": "Arábia",
    "Aztec": "Astecas",
    "China": "China",
    "Egypt": "Egito",
    "England": "Inglaterra",
    "France": "França",
    "Germany": "Alemanha",
    "Greece": "Grécia",
    "India": "Índia",
    "Iroquois": "Iroqueses",
    "Japan": "Japão",
    "Ottoman": "Império Otomano",
    "Persia": "Pérsia",
    "Rome": "Roma",
    "Russia": "Rússia",
    "Siam": "Sião",
    "Songhai": "Songai"
  }
}
